{
    "form":{
        "bind_type":"eligible_couple",
        "default_bind_path":"/model/instance/ANC_Registration_EngKan/",
        "fields":[
            {
                "name":"id",
                "value":"<%= ec['Entity ID'] %>",
                "source":"eligible_couple.id"
            },
            {
                "name":"motherId",
                "value":"<%= anc['Entity ID'] %>",
                "source":"eligible_couple.mother.id"
            },
            {
                "name":"registrationDate",
                "value":"<%= anc['Registration date'] %>",
                "source":"eligible_couple.mother.registrationDate"
            },
            {
                "name":"registrationPlace",
                "value":"<%= anc['Registration place'] %>",
                "source":"eligible_couple.mother.registrationPlace"
            },
            {
                "name":"wifeName",
                "value":"<%= anc['Wife Name'] %>",
                "source":"eligible_couple.wifeName"
            },
            {
                "name":"numberOfPregnancies",
                "source":"eligible_couple.numberOfPregnancies"
            },
            {
                "name":"thayiCardNumber",
                "value":"<%= anc['Thayi number'] %>",
                "source":"eligible_couple.mother.thayiCardNumber"
            },
            {
                "name":"ancNumber",
                "value":"<%= anc['ANC number'] %>",
                "source":"eligible_couple.mother.ancNumber"
            },
            {
                "name":"isJSYBeneficiary",
                "value":"<%= anc['JSY'] %>",
                "source":"eligible_couple.mother.isJSYBeneficiary"
            },
            {
                "name":"ashaName",
                "source":"eligible_couple.mother.ashaName"
            },
            {
                "name":"ashaPhoneNumber",
                "source":"eligible_couple.mother.ashaPhoneNumber"
            },
            {
                "name":"referenceDate",
                "value":"<%= anc['Reference date'] %>",
                "source":"eligible_couple.mother.referenceDate"
            },
            {
                "name":"edd",
                "value":"<%= anc['EDD'] %>",
                "source":"eligible_couple.mother.edd"
            },
            {
                "name":"linkedFacilityForDelivery",
                "source":"eligible_couple.mother.linkedFacilityForDelivery"
            },
            {
                "name":"facilityName",
                "source":"eligible_couple.mother.facilityName"
            },
            {
                "name":"complications",
                "source":"eligible_couple.mother.complications"
            },
            {
                "name":"otherComplications",
                "source":"eligible_couple.mother.otherComplication"
            },
            {
                "name":"medicalHistories",
                "source":"eligible_couple.mother.medicalHistories"
            },
            {
                "name":"otherMedicalHistories",
                "source":"eligible_couple.mother.otherMedicalHistories"
            },
            {
                "name":"bloodGroup",
                "source":"eligible_couple.mother.bloodGroup"
            },
            {
                "name":"isRHNegative",
                "source":"eligible_couple.mother.isRHNegative"
            },
            {
                "name":"husbandBloodGroup",
                "source":"eligible_couple.mother.husbandBloodGroup"
            },
            {
                "name":"isRHIncompatibleCouple",
                "source":"eligible_couple.mother.isRHIncompatibleCouple"
            },
            {
                "name":"height",
                "source":"eligible_couple.mother.height"
            },
            {
                "name":"weight",
                "source":"eligible_couple.mother.weight"
            },
            {
                "name":"isTobaccoUsed",
                "source":"eligible_couple.mother.isTobaccoUsed"
            },
            {
                "name":"tobaccoUser",
                "source":"eligible_couple.mother.tobaccoUser"
            },
            {
                "name":"isHighRiskTillDelivery",
                "source":"eligible_couple.mother.isHighRiskTillDelivery"
            },
            {
                "name":"highRiskTillDeliveryReason",
                "source":"eligible_couple.mother.highRiskTillDeliveryReason"
            },
            {
                "name":"isHighRiskTillPNCClose",
                "source":"eligible_couple.mother.isHighRiskTillPNCClose"
            },
            {
                "name":"highRiskTillPNCCloseReason",
                "source":"eligible_couple.mother.highRiskTillPNCCloseReason"
            },
            {
                "name":"highRiskReason",
                "value":"<%= anc['HRP reasons'] %>",
                "source":"eligible_couple.mother.highRiskReason"
            },
            {
                "name":"isHighRisk",
                "value":"<%= anc['HRP'] %>",
                "source":"eligible_couple.mother.isHighRisk"
            },
            {
                "name":"submissionDate",
                "value":"<%= anc['Registration date'] %>",
                "source":"eligible_couple.mother.submissionDate"
            },
            {
                "name":"type",
                "value":"ANC",
                "source":"eligible_couple.mother.type"
            },
            {
                "name":"isClosed",
                "value":"false",
                "source":"eligible_couple.mother.isClosed"
            },
            {
                "name":"currentMethod",
                "value":"",
                "source":"eligible_couple.currentMethod"
            },
            {
                "name":"familyPlanningMethodChangeDate",
                "value":"",
                "source":"eligible_couple.familyPlanningMethodChangeDate"
            }
        ]
    }
}